lineagebundle/LineageBundle.py
lineagebundle/LineageBundleTest.py
lineagebundle/_config/config.yaml
lineagebundle/_config/config_test.yaml
lineagebundle/database/DatabasePublisher.py
lineagebundle/database/LineageDatabaseInitCommand.py
lineagebundle/database/LineageDatabasePublisherCommand.py
lineagebundle/html/HTMLCreator.py
lineagebundle/html/LineageHTMLPublisherCommand.py
lineagebundle/html/NotebookDetailHTMLParser.py
lineagebundle/html/PipelinesHTMLParser.py
lineagebundle/html/templates/template.html
lineagebundle/image/LineageImagePublisherCommand.py
lineagebundle/json/LineageJSONPublisherCommand.py
lineagebundle/lineage/LineageGenerator.py
lineagebundle/notebook/FunctionCollector.py
lineagebundle/notebook/LayerResolver.py
lineagebundle/notebook/LayerResolverTest.py
lineagebundle/notebook/Notebook.py
lineagebundle/notebook/NotebookCreationFacade.py
lineagebundle/notebook/NotebookFunctionsLineageGenerator.py
lineagebundle/notebook/NotebookList.py
lineagebundle/notebook/NotebookParser.py
lineagebundle/notebook/NotebookParserTest.py
lineagebundle/notebook/NotebookParserTest_sample/linked_function_sample.py
lineagebundle/notebook/NotebookParserTest_sample/read_table_sample.py
lineagebundle/notebook/NotebookParserTest_sample/table_params_sample.py
lineagebundle/notebook/NotebookParserTest_sample/table_writer_sample.py
lineagebundle/notebook/NotebooksLocator.py
lineagebundle/notebook/dag/DagCreator.py
lineagebundle/notebook/dag/Functions2DagMapper.py
lineagebundle/notebook/decorator/DecoratorParserResolver.py
lineagebundle/notebook/decorator/Function.py
lineagebundle/notebook/decorator/ParsedDecorator.py
lineagebundle/notebook/function/NotebookFunction.py
lineagebundle/notebook/function/NotebookFunctionsRelation.py
lineagebundle/notebook/function/ParsedNotebookFunction.py
lineagebundle/notebook/function/ParsedNotebookFunctionsRelation.py
lineagebundle/orchestration/OrchestrationGenerateNotebookCommand.py
lineage_bundle-1.2.1.dist-info/entry_points.txt
lineage_bundle-1.2.1.dist-info/LICENSE
lineage_bundle-1.2.1.dist-info/WHEEL
lineage_bundle-1.2.1.dist-info/METADATA
lineage_bundle-1.2.1.dist-info/RECORD
