Metadata-Version: 2.1
Name: lineage-bundle
Version: 1.2.1
Summary: Lineage generation bundle
Home-page: https://github.com/daipe-ai/lineage-bundle
License: Proprietary
Author: Datasentics
Author-email: jiri.koutny@datasentics.com
Requires-Python: >=3.7,<4.0
Classifier: License :: Other/Proprietary License
Classifier: Operating System :: OS Independent
Classifier: Programming Language :: Python :: 3
Classifier: Programming Language :: Python :: 3.7
Classifier: Programming Language :: Python :: 3.8
Classifier: Programming Language :: Python :: 3.9
Requires-Dist: SQLAlchemy (>=1.3,<2.0)
Requires-Dist: console-bundle (>=0.5,<0.6)
Requires-Dist: daipe-core (>=1.2,<2.0)
Requires-Dist: networkx (>=2.6.3,<3.0.0)
Requires-Dist: pyfony-bundles (>=0.4.0,<0.5.0)
Requires-Dist: pyfony-sqlalchemy-bundle (>=1.0.0,<2.0.0)
Project-URL: Repository, https://github.com/daipe-ai/lineage-bundle
